yarr/__init__.py
yarr/yarr.py
yarr-0.9.0.dist-info/LICENSE
yarr-0.9.0.dist-info/METADATA
yarr-0.9.0.dist-info/WHEEL
yarr-0.9.0.dist-info/top_level.txt
yarr-0.9.0.dist-info/RECORD
