Metadata-Version: 2.1
Name: yarr
Version: 0.9.0
Summary: A simple and fast RPC framework
Home-page: https://git.sr.ht/~maep/yarr
Author: Bartholomew Roberts
Author-email: git@maeppi.e4ward.com
License: WTFPL
Platform: UNKNOWN
Classifier: Development Status :: 4 - Beta
Classifier: Intended Audience :: Developers
Classifier: Operating System :: OS Independent
Classifier: Programming Language :: Python :: 3
Classifier: Topic :: System :: Networking
Requires-Python: >= 3.1
